cli/__init__.py
cli/__main__.py
cli/apply.py
cli/inspect.py
cli/prune.py
cli/reconcile.py
koreo-0.3.3.dist-info/METADATA
koreo-0.3.3.dist-info/WHEEL
koreo-0.3.3.dist-info/entry_points.txt
koreo-0.3.3.dist-info/licenses/LICENSE
koreo_tooling/__init__.py
koreo_tooling/analysis.py
koreo_tooling/constants.py
koreo_tooling/function_test.py
koreo_tooling/indexing/__init__.py
koreo_tooling/indexing/cel_semantics.py
koreo_tooling/indexing/extractor.py
koreo_tooling/indexing/koreo_semantics.py
koreo_tooling/indexing/semantics.py
koreo_tooling/langserver/codelens.py
koreo_tooling/langserver/fileprocessor.py
koreo_tooling/langserver/function_test.py
koreo_tooling/langserver/hover.py
koreo_tooling/langserver/orchestrator.py
koreo_tooling/langserver/rangers.py
koreo_tooling/langserver/workflow.py
koreo_tooling/server.py
koreo-0.3.3.dist-info/RECORD
