Metadata-Version: 2.1
Name: koreo
Version: 0.3.3
Summary: Tooling package for Koreo
Author-Email: Robert Kluin <robert.kluin@realkinetic.com>, Eric Larssen <eric.larssen@realkinetic.com>, Tyler Treat <tyler.treat@realkinetic.com>
License: Apache-2.0
Project-URL: Homepage, https://koreo.dev
Requires-Python: >=3.13
Requires-Dist: cel-python==0.3.0
Requires-Dist: pygls==2.0.0a2
Requires-Dist: pyyaml==6.0.2
Requires-Dist: koreo-core==0.1.14
Requires-Dist: colorist>=1.8.3
Requires-Dist: kr8s>=0.20.6
